Sakesama_SpeechToText/__init__.py
Sakesama3-0.2.dist-info/METADATA
Sakesama3-0.2.dist-info/WHEEL
Sakesama3-0.2.dist-info/top_level.txt
Sakesama3-0.2.dist-info/RECORD
